imlresi/__init__.py
imlresi/trace.py
imlresi-0.0.6.dist-info/LICENSE
imlresi-0.0.6.dist-info/METADATA
imlresi-0.0.6.dist-info/WHEEL
imlresi-0.0.6.dist-info/entry_points.txt
imlresi-0.0.6.dist-info/top_level.txt
imlresi-0.0.6.dist-info/RECORD
